{
    "/assets/css/main.css": "/assets/css/main.css?id=0ab2933ed2efe9dfb816",
    "/assets/css/editor.css": "/assets/css/editor.css?id=7d40a3a9390e3a2b34dd",
    "/assets/css/woocommerce.css": "/assets/css/woocommerce.css?id=73c241415800bc2f85b6",
    "/assets/css/metaslider.css": "/assets/css/metaslider.css?id=c3dffdf3450ab9ab8e0b",
    "/assets/css/ninja-forms.css": "/assets/css/ninja-forms.css?id=d83aab7c76f001d83565",
    "/assets/js/min/editor.js": "/assets/js/min/editor.js?id=a6f477682e749175affa",
    "/assets/js/min/main.js": "/assets/js/min/main.js?id=5320ad66dfcfbf3c9675"
}
